storm_aws_adfs/__init__.py
storm_aws_adfs/_azure_cloud_mfa_authenticator.py
storm_aws_adfs/_azure_mfa_authenticator.py
storm_aws_adfs/_duo_authenticator.py
storm_aws_adfs/_rsa_authenticator.py
storm_aws_adfs/_symantec_vip_access.py
storm_aws_adfs/account_aliases_fetcher.py
storm_aws_adfs/authenticator.py
storm_aws_adfs/commands.py
storm_aws_adfs/helpers.py
storm_aws_adfs/html_roles_fetcher.py
storm_aws_adfs/list_profiles.py
storm_aws_adfs/login.py
storm_aws_adfs/prepare.py
storm_aws_adfs/reset.py
storm_aws_adfs/role_chooser.py
storm_aws_adfs/roles_assertion_extractor.py
storm_aws_adfs-1.0.0.dist-info/entry_points.txt
storm_aws_adfs-1.0.0.dist-info/LICENSE
storm_aws_adfs-1.0.0.dist-info/WHEEL
storm_aws_adfs-1.0.0.dist-info/METADATA
storm_aws_adfs-1.0.0.dist-info/RECORD
