Metadata-Version: 2.1
Name: storm-aws-adfs
Version: 1.0.0
Summary: AWS CLI authenticator via ADFS - small command-line tool to authenticate via ADFS and assume chosen role
Keywords: aws,adfs,console,tool
Author: Federico BARBERO
Author-email: f.barbero@reply.it
Requires-Python: >=3.6,<4.0
Classifier: Development Status :: 5 - Production/Stable
Classifier: Environment :: Console
Classifier: Intended Audience :: Developers
Classifier: Intended Audience :: End Users/Desktop
Classifier: Intended Audience :: System Administrators
Classifier: License :: OSI Approved :: Python Software Foundation License
Classifier: Operating System :: MacOS :: MacOS X
Classifier: Operating System :: Microsoft :: Windows
Classifier: Operating System :: POSIX
Classifier: Programming Language :: Python :: 3
Classifier: Programming Language :: Python :: 3.10
Classifier: Programming Language :: Python :: 3.6
Classifier: Programming Language :: Python :: 3.7
Classifier: Programming Language :: Python :: 3.8
Classifier: Programming Language :: Python :: 3.9
Requires-Dist: boto3 (>=1.20.50,<2.0.0)
Requires-Dist: botocore (>=1.12.6)
Requires-Dist: click
Requires-Dist: configparser
Requires-Dist: fido2 (>=0.9.3)
Requires-Dist: lxml
Requires-Dist: requests
Requires-Dist: requests-kerberos; platform_system != "Windows"
Requires-Dist: requests-negotiate-sspi (>=0.3.4); platform_system == "Windows"
